MANIFEST.in
ipwc
ipwc.py
setup.cfg
setup.py
PowerConsole.egg-info/PKG-INFO
PowerConsole.egg-info/SOURCES.txt
PowerConsole.egg-info/dependency_links.txt
PowerConsole.egg-info/namespace_packages.txt
PowerConsole.egg-info/requires.txt
PowerConsole.egg-info/top_level.txt
docs/.buildinfo
docs/concept.html
docs/genindex.html
docs/index.html
docs/modindex.html
docs/new-commands.html
docs/objects.inv
docs/pwc.html
docs/search.html
docs/searchindex.js
docs/stdcmd.html
docs/_sources/concept.txt
docs/_sources/index.txt
docs/_sources/new-commands.txt
docs/_sources/pwc.txt
docs/_sources/stdcmd.txt
docs/_static/basic.css
docs/_static/default.css
docs/_static/doctools.js
docs/_static/file.png
docs/_static/jquery.js
docs/_static/minus.png
docs/_static/plus.png
docs/_static/pygments.css
docs/_static/searchtools.js
pwc/Itpl.py
pwc/__init__.py
pwc/base.py
pwc/interpreter.py
pwc/release.py
pwc/stdcmd.py
sphinx/Makefile
sphinx/concept.txt
sphinx/conf.py
sphinx/index.txt
sphinx/make.bat
sphinx/new-commands.txt
sphinx/pwc.txt
sphinx/stdcmd.txt