Metadata-Version: 1.0
Name: PowerConsole
Version: 0.7.5
Summary: Advanced Command Console
Home-page: http://www.ibphoenix.cz/pwc/index.html
Author: Pavel Cisar
Author-email: pcisar@users.sourceforge.net
License: IDPL 1.0 <http://www.firebirdsql.org/index.php?op=doc&id=idpl>
Download-URL: http://ibphoenix.cz/pwc/download/
Platform: UNKNOWN
Classifier: Development Status :: 5 - Production/Stable
Classifier: Operating System :: OS Independent
Classifier: Programming Language :: Python
Classifier: Topic :: Software Development :: Interpreters
Classifier: Topic :: Software Development :: Libraries :: Python Modules
Classifier: License :: OSI Approved
